cutt_sd/__init__.py
cutt_sd/checker.py
cutt_sd/config.py
cutt_sd/server.py
cutt_sd/service.py
cutt_sd/zk.py
cutt_sd-0.0.5.dist-info/METADATA
cutt_sd-0.0.5.dist-info/RECORD
cutt_sd-0.0.5.dist-info/WHEEL
cutt_sd-0.0.5.dist-info/top_level.txt
