Metadata-Version: 2.1
Name: cutt-sd
Version: 0.0.5
Summary: zk service discovery
Home-page: https://github.com/ourbest/cutt_sd
Author: YHC
Author-email: chenyonghui@gmail.com
License: UNKNOWN
Platform: UNKNOWN
Classifier: Programming Language :: Python :: 3
Classifier: License :: OSI Approved :: MIT License
Classifier: Operating System :: OS Independent
Requires-Dist: requests
Requires-Dist: kazoo
Requires-Dist: flask
